{
  "constituencyNumber": 29,
  "elections": [
    {
      "year": 2011,
      "type": "general",
      "reason": null,
      "candidates": [
        {
          "name": "Elamaram Kareem",
          "party": "Communist Party of India (Marxist)",
          "votes": 60550,
          "votePct": 46.8,
          "alliance": "LDF"
        },
        {
          "name": "Adam Mulsi M. P.",
          "party": "Indian National Congress",
          "votes": 55234,
          "votePct": 42.69,
          "alliance": "UDF"
        },
        {
          "name": "K. P. Sreesan",
          "party": "Bharatiya Janata Party",
          "votes": 11040,
          "votePct": 8.53,
          "alliance": "NDA"
        },
        {
          "name": "Muhammed Musthafa",
          "party": "Social Democratic Party Of India",
          "votes": 954,
          "votePct": 0.74,
          "alliance": "OTHER"
        },
        {
          "name": "K. S. Hariharan",
          "party": "Independent",
          "votes": 564,
          "votePct": 0.44,
          "alliance": "OTHER"
        }
      ],
      "margin": 5316,
      "marginPct": 4.11,
      "turnout": 129390,
      "turnoutPct": 78.87,
      "result": "CPI(M) hold"
    },
    {
      "year": 2016,
      "type": "general",
      "reason": null,
      "candidates": [
        {
          "name": "V. K. C. Mammed Koya",
          "party": "Communist Party of India (Marxist)",
          "votes": 69114,
          "votePct": 44.39,
          "alliance": "LDF"
        },
        {
          "name": "M. P. Adam Mulsi",
          "party": "Indian National Congress",
          "votes": 54751,
          "votePct": 35.16,
          "alliance": "UDF"
        },
        {
          "name": "Prakash Babu",
          "party": "Bharatiya Janata Party",
          "votes": 27958,
          "votePct": 17.96,
          "alliance": "NDA"
        },
        {
          "name": "P. C. Muhammedkutty Master",
          "party": "Welfare Party of India",
          "votes": 1387,
          "votePct": 0.89,
          "alliance": "OTHER"
        },
        {
          "name": "Musthafa Kommeri",
          "party": "Social Democratic Party Of India",
          "votes": 1126,
          "votePct": 0.72,
          "alliance": "OTHER"
        },
        {
          "name": "V. K. Mammed Koya V K House",
          "party": "Independent",
          "votes": 355,
          "votePct": 0.23,
          "alliance": "OTHER"
        },
        {
          "name": "Adam Malique",
          "party": "Independent",
          "votes": 199,
          "votePct": 0.13,
          "alliance": "OTHER"
        },
        {
          "name": "K. V. Adam",
          "party": "Independent",
          "votes": 109,
          "votePct": 0.07,
          "alliance": "OTHER"
        },
        {
          "name": "Ajeesh Kumar Erakkathil",
          "party": "Independent",
          "votes": 105,
          "votePct": 0.07,
          "alliance": "OTHER"
        }
      ],
      "margin": 14363,
      "marginPct": 9.22,
      "turnout": 155710,
      "turnoutPct": 81.53,
      "result": "CPI(M) hold"
    },
    {
      "year": 2021,
      "type": "general",
      "reason": null,
      "candidates": [
        {
          "name": "P. A. Muhammed Riyas",
          "party": "Communist Party of India (Marxist)",
          "votes": 82165,
          "votePct": 49.73,
          "alliance": "LDF"
        },
        {
          "name": "P. M. Niyas",
          "party": "Indian National Congress",
          "votes": 53418,
          "votePct": 32.33,
          "alliance": "UDF"
        },
        {
          "name": "Prakash Babu",
          "party": "Bharatiya Janata Party",
          "votes": 26267,
          "votePct": 15.9,
          "alliance": "NDA"
        },
        {
          "name": "Jamal Chaliyam",
          "party": "Social Democratic Party Of India",
          "votes": 2029,
          "votePct": 1.23,
          "alliance": "OTHER"
        },
        {
          "name": "NOTA",
          "party": "None of the Above",
          "votes": 621,
          "votePct": 0.38,
          "alliance": "NOTA"
        },
        {
          "name": "K. K. Abdul Gafoor",
          "party": "Bahujan Samaj Party",
          "votes": 272,
          "votePct": 0.16,
          "alliance": "OTHER"
        },
        {
          "name": "P. P. Muhammed Riyas s/o Mamukoya",
          "party": "Independent",
          "votes": 165,
          "votePct": 0.1,
          "alliance": "OTHER"
        },
        {
          "name": "E. M. Niyas s/o Saleem Babu",
          "party": "Independent",
          "votes": 162,
          "votePct": 0.1,
          "alliance": "OTHER"
        },
        {
          "name": "K. Niyaz s/o Koya Kunnil",
          "party": "Independent",
          "votes": 111,
          "votePct": 0.07,
          "alliance": "OTHER"
        }
      ],
      "margin": 28747,
      "marginPct": 17.4,
      "turnout": 165210,
      "turnoutPct": 79.41,
      "result": "CPI(M) hold"
    }
  ]
}
